[
    {
        "fuel_type": "RocketFuel",
        "fuel_cost": 91.8,
        "adjusted_fuel_cost": 198.0,
        "fuelTankRatio": 8.0,
        "fuelRatio": 0.005
    },
    {
        "fuel_type": "LiquidFuel",
        "fuel_cost": 160.0,
        "adjusted_fuel_cost": 344.0,
        "fuelTankRatio": 7,
        "fuelRatio": 0.005
    },
    {
        "fuel_type": "MonoPropellant",
        "fuel_cost": 300.0,
        "adjusted_fuel_cost": 618.0,
        "fuelTankRatio": 6,
        "fuelRatio": 0.004
    },
    {
        "fuel_type": "SolidFuel",
        "fuel_cost": 80.0,
        "fuelRatio": 0.0075
    },
    {
        "fuel_type": "XenonGas",
        "fuel_cost": 40000.0,
        "adjusted_fuel_cost": 44249.0,
        "fuelTankRatio": 3,
        "fuelRatio": 0.0001
    }
]